{
  "candidates": [
    {
      "formatted_address": "日本、〒389-2411 長野県飯山市豊田６３６２−１",
      "geometry": {
        "location": {
          "lat": 36.9319941,
          "lng": 138.3878759
        },
        "viewport": {
          "northeast": {
            "lat": 36.93332502989273,
            "lng": 138.3891322298927
          },
          "southwest": {
            "lat": 36.93062537010729,
            "lng": 138.3864325701072
          }
        }
      },
      "icon": "https://maps.gstatic.com/mapfiles/place_api/icons/v1/png_71/geocode-71.png",
      "name": "〒389-2411 長野県飯山市豊田６３６２−１",
      "place_id": "ChIJ0wEbgQwQ9l8RQ95qzOP4cZs",
      "plus_code": {
        "compound_code": "W9JQ+Q5 飯山市、長野県",
        "global_code": "8Q8WW9JQ+Q5"
      },
      "types": [
        "street_address"
      ]
    }
  ],
  "status": "OK"
}