{
  "candidates": [
    {
      "business_status": "OPERATIONAL",
      "formatted_address": "日本、〒386-0601 長野県小県郡長和町大門２７８−１",
      "geometry": {
        "location": {
          "lat": 36.2341622,
          "lng": 138.2535798
        },
        "viewport": {
          "northeast": {
            "lat": 36.23551087989272,
            "lng": 138.2548738798927
          },
          "southwest": {
            "lat": 36.23281122010728,
            "lng": 138.2521742201073
          }
        }
      },
      "icon": "https://maps.gstatic.com/mapfiles/place_api/icons/v1/png_71/cafe-71.png",
      "name": "天然酵母パンむく堂",
      "photos": [
        {
          "height": 4032,
          "html_attributions": [
            "<a href=\"https://maps.google.com/maps/contrib/106841978162309920604\">A Google User</a>"
          ],
          "photo_reference": "Aap_uEAYkjWZ8dzmN6RJZvwbPnqVr2KyWSV0zYvhU04JuAx9BV-YXGr55DE3KIAcpMYyIFDFdKX5mtXAhZhG4kU6rmFrcxe8rRGyBaKUsTQOx9l3SuAAtfcDmudSjp4_xHJcpHwHMsa1h9fhCjW7FK66u5_J1vEaqWtBMk1-sNQ8FHsxQuDr",
          "width": 3024
        }
      ],
      "place_id": "ChIJmeTWe-6xHWARZw7mBY3u-xw",
      "plus_code": {
        "compound_code": "67M3+MC 長和町、長野県",
        "global_code": "8Q8W67M3+MC"
      },
      "types": [
        "cafe",
        "store",
        "food",
        "point_of_interest",
        "establishment"
      ]
    }
  ],
  "status": "OK"
}