{
  "candidates": [
    {
      "business_status": "OPERATIONAL",
      "formatted_address": "日本、〒384-0025 長野県小諸市相生町１丁目３−１",
      "geometry": {
        "location": {
          "lat": 36.3270733,
          "lng": 138.4224505
        },
        "viewport": {
          "northeast": {
            "lat": 36.32842757989273,
            "lng": 138.4237949798927
          },
          "southwest": {
            "lat": 36.32572792010728,
            "lng": 138.4210953201072
          }
        }
      },
      "icon": "https://maps.gstatic.com/mapfiles/place_api/icons/v1/png_71/shopping-71.png",
      "name": "おみやげのみやさか",
      "photos": [
        {
          "height": 3648,
          "html_attributions": [
            "<a href=\"https://maps.google.com/maps/contrib/108961248143646638949\">Clayfield Xvi</a>"
          ],
          "photo_reference": "Aap_uEB3aRAWuYjjVX9pucZHMYU-N188vlVlG1hxRDGfA4WHBma0oMMYUv2vuOyiLFo3WBIPEYGuyOLzLU5ZRIzO-gHdaTvMNdm0JmeUrbalsILhqs1YKNXj4vYC8tUz3hSaVR6YkaOEftZNPoD98FrTk74vvKy-pCqc6Triu1IgEfRxSzcV",
          "width": 5472
        }
      ],
      "place_id": "ChIJMfyNl7bJHWARqsr7Zji7c5Y",
      "plus_code": {
        "compound_code": "8CGC+QX 小諸市、長野県",
        "global_code": "8Q8W8CGC+QX"
      },
      "types": [
        "point_of_interest",
        "store",
        "establishment"
      ]
    }
  ],
  "status": "OK"
}