{
  "candidates": [
    {
      "business_status": "OPERATIONAL",
      "formatted_address": "日本、〒389-0102 長野県北佐久郡軽井沢町軽井沢",
      "geometry": {
        "location": {
          "lat": 36.3407074,
          "lng": 138.6360469
        },
        "viewport": {
          "northeast": {
            "lat": 36.34389079999998,
            "lng": 138.63983565
          },
          "southwest": {
            "lat": 36.33751600000001,
            "lng": 138.62817825
          }
        }
      },
      "icon": "https://maps.gstatic.com/mapfiles/place_api/icons/v1/png_71/shopping-71.png",
      "name": "軽井沢・プリンスショッピングプラザ",
      "photos": [
        {
          "height": 3096,
          "html_attributions": [
            "<a href=\"https://maps.google.com/maps/contrib/115820662855144814258\">鹿野雅士</a>"
          ],
          "photo_reference": "Aap_uEC1RF_s8naJYBeQzrE_DBFRBlv4YzmNJZPDnRqZlq-LY0wNJMjKAVExY-Jhj5t8CdI_VI6IqaSi95xAbCoTtyoQCtre_ZUXwA2-qAoxt6eT4y90gJQjesxl9tUHMVABl8va5HWa5zT6ZNr6czfA-1Tk1a62o-vDmYOKA7O9fzqKHPTT",
          "width": 4128
        }
      ],
      "place_id": "ChIJs2bRqHvTHWARcl6bPa7ly-g",
      "plus_code": {
        "compound_code": "8JRP+7C 軽井沢町、長野県",
        "global_code": "8Q8W8JRP+7C"
      },
      "types": [
        "shopping_mall",
        "point_of_interest",
        "establishment"
      ]
    }
  ],
  "status": "OK"
}