{
  "candidates": [
    {
      "business_status": "OPERATIONAL",
      "formatted_address": "日本、〒389-0102 長野県北佐久郡軽井沢町軽井沢４６９−４",
      "geometry": {
        "location": {
          "lat": 36.3528075,
          "lng": 138.6345425
        },
        "viewport": {
          "northeast": {
            "lat": 36.35415352989272,
            "lng": 138.6357564798927
          },
          "southwest": {
            "lat": 36.35145387010728,
            "lng": 138.6330568201073
          }
        }
      },
      "icon": "https://maps.gstatic.com/mapfiles/place_api/icons/v1/png_71/restaurant-71.png",
      "name": "レストラン アルペジオ（ルグラン旧軽井沢）",
      "photos": [
        {
          "height": 1365,
          "html_attributions": [
            "<a href=\"https://maps.google.com/maps/contrib/114810204411795056365\">Arpeggio</a>"
          ],
          "photo_reference": "Aap_uECiZf-JkAbkTHyJXqw46wefh39VHfDu0oHgNYZQ9qfEtg1pVdo3-3LobIw4fKPuYLNtmczim5n09A7QJOc-lIGbJoAM5zdwDLI9CTQbZHjplesX0cDGN_mZxn3nfKoz0I0PlQoEIfVeA2YiqH9Cgc_xrUTLwY72zl2y7qR1E2nl68yE",
          "width": 2048
        }
      ],
      "place_id": "ChIJQURuZoHTHWARDE4hwh6qUIw",
      "plus_code": {
        "compound_code": "9J3M+4R 軽井沢町、長野県",
        "global_code": "8Q8W9J3M+4R"
      },
      "types": [
        "restaurant",
        "food",
        "point_of_interest",
        "establishment"
      ]
    },
    {
      "business_status": "OPERATIONAL",
      "formatted_address": "日本、〒389-0102 長野県北佐久郡軽井沢町軽井沢４６９−４",
      "geometry": {
        "location": {
          "lat": 36.3528173,
          "lng": 138.6345427
        },
        "viewport": {
          "northeast": {
            "lat": 36.35421572989272,
            "lng": 138.6357538298927
          },
          "southwest": {
            "lat": 36.35151607010728,
            "lng": 138.6330541701073
          }
        }
      },
      "icon": "https://maps.gstatic.com/mapfiles/place_api/icons/v1/png_71/lodging-71.png",
      "name": "ルグラン旧軽井沢",
      "photos": [
        {
          "height": 900,
          "html_attributions": [
            "<a href=\"https://maps.google.com/maps/contrib/113641086702856137436\">ルグラン軽井沢</a>"
          ],
          "photo_reference": "Aap_uED0xEB2fZZW5SAvd4Bu5fn1a5745lihoZxOWZQvKbAdCDgmtSxz7jY4Z4WXeSgmoOCGGEQR3KfRyZSV44SmzL7PjMKJB0wD3bd1p7-08QTzyh2QScbSnwQHujPlxN8B4VVY0-lQleTZDb1WDdSvxcYUEnJuZ3KNHymTSVOV6C7bhDo4",
          "width": 1200
        }
      ],
      "place_id": "ChIJQURuZoHTHWAR1z0Kv5RujbQ",
      "plus_code": {
        "compound_code": "9J3M+4R 軽井沢町、長野県",
        "global_code": "8Q8W9J3M+4R"
      },
      "types": [
        "lodging",
        "point_of_interest",
        "establishment"
      ]
    }
  ],
  "status": "OK"
}