{
  "candidates": [
    {
      "business_status": "OPERATIONAL",
      "formatted_address": "日本、〒389-0102 長野県北佐久郡軽井沢町軽井沢９２５ 万平ホテル内",
      "geometry": {
        "location": {
          "lat": 36.3576215,
          "lng": 138.6417961
        },
        "viewport": {
          "northeast": {
            "lat": 36.35886757989272,
            "lng": 138.6430127798927
          },
          "southwest": {
            "lat": 36.35616792010727,
            "lng": 138.6403131201073
          }
        }
      },
      "icon": "https://maps.gstatic.com/mapfiles/place_api/icons/v1/png_71/bar-71.png",
      "name": "万平ホテル ザ・バー",
      "photos": [
        {
          "height": 960,
          "html_attributions": [
            "<a href=\"https://maps.google.com/maps/contrib/108928848131044691424\">A Google User</a>"
          ],
          "photo_reference": "Aap_uEA3mUzAPW0zSqdTL6bjNtAwOen-ipMu-lzcgNaok0tkzHY3KXIACog9ZT6GzNm0sm5Qys-0x8ibnkQa7-K7TPT_xRhPVIlPf0tUkp9qPqtznu73uVY2pyaGNsfI3yJoQ8eECQ3kXUCHINxtzXD1JWlmR4eNIZdyl30GdP3FZRFOVLJ9",
          "width": 720
        }
      ],
      "place_id": "ChIJA4TXj0fVHWARQ2k6WfCHL-0",
      "plus_code": {
        "compound_code": "9J5R+2P 軽井沢町、長野県",
        "global_code": "8Q8W9J5R+2P"
      },
      "types": [
        "bar",
        "point_of_interest",
        "establishment"
      ]
    }
  ],
  "status": "OK"
}