{
  "candidates": [
    {
      "business_status": "OPERATIONAL",
      "formatted_address": "日本、〒389-0111 長野県北佐久郡軽井沢町長倉２３４８−１２",
      "geometry": {
        "location": {
          "lat": 36.3514405,
          "lng": 138.5998737
        },
        "viewport": {
          "northeast": {
            "lat": 36.35280257989272,
            "lng": 138.6012066798927
          },
          "southwest": {
            "lat": 36.35010292010728,
            "lng": 138.5985070201072
          }
        }
      },
      "icon": "https://maps.gstatic.com/mapfiles/place_api/icons/v1/png_71/lodging-71.png",
      "name": "ベルキャビン ゲストハウス",
      "photos": [
        {
          "height": 1702,
          "html_attributions": [
            "<a href=\"https://maps.google.com/maps/contrib/102380948896889900742\">ベルキャビン カフェ＆ゲストハウス</a>"
          ],
          "photo_reference": "Aap_uEBYhBmOj0BWH4VtzqH3JJrFaN-5QLqnt5tl43zxjfGz19LVaenUD9bxpuJzxReBbNhjELaKI93kX3xzGb8nBSFxcPH9jA50PTufkVH1H1h3OKgr7ge_dvYtG0S0xWOU_EdcSxzatjBhiQoYQkBgDpaJXwMdErrlr7sx_ZVueT1_waJB",
          "width": 3024
        }
      ],
      "place_id": "ChIJF-oXPbXTHWARE27J_CkXMzc",
      "plus_code": {
        "compound_code": "9H2X+HX 軽井沢町、長野県",
        "global_code": "8Q8W9H2X+HX"
      },
      "types": [
        "lodging",
        "point_of_interest",
        "establishment"
      ]
    }
  ],
  "status": "OK"
}