{
  "candidates": [
    {
      "business_status": "OPERATIONAL",
      "formatted_address": "日本、〒390-1520 長野県松本市安曇４０８５−４９",
      "geometry": {
        "location": {
          "lat": 36.1235025,
          "lng": 137.6381931
        },
        "viewport": {
          "northeast": {
            "lat": 36.12478167989272,
            "lng": 137.6396138298927
          },
          "southwest": {
            "lat": 36.12208202010728,
            "lng": 137.6369141701072
          }
        }
      },
      "icon": "https://maps.gstatic.com/mapfiles/place_api/icons/v1/png_71/lodging-71.png",
      "name": "温泉宿 美鈴荘",
      "photos": [
        {
          "height": 723,
          "html_attributions": [
            "<a href=\"https://maps.google.com/maps/contrib/100039806386686504984\">A Google User</a>"
          ],
          "photo_reference": "Aap_uEB72eOCXwoOx6_1eIcHC_KfQqAB93bYnUqx3TKuLTlKFkC-T8mUe9L_bGqlwMfFHR_5qKHzwZ1T0VZB2h-f0FDk-CE0BJ2ClpKUcVZrRIiIjcwzcLMOs-yw7foxWMkFYJxa_MR6vuOVu-jHivpfwlSfKg0kEuFQE9lxorAjNPfCRjDl",
          "width": 1087
        }
      ],
      "place_id": "ChIJf6XC_6I5HWARpBt8n6GgrMQ",
      "plus_code": {
        "compound_code": "4JFQ+C7 松本市、長野県",
        "global_code": "8Q8V4JFQ+C7"
      },
      "types": [
        "lodging",
        "point_of_interest",
        "establishment"
      ]
    }
  ],
  "status": "OK"
}