{
  "candidates": [
    {
      "business_status": "OPERATIONAL",
      "formatted_address": "日本、〒399-0036 長野県松本市村井町南１丁目７−４",
      "geometry": {
        "location": {
          "lat": 36.1814316,
          "lng": 137.9622823
        },
        "viewport": {
          "northeast": {
            "lat": 36.18274877989271,
            "lng": 137.9637540298927
          },
          "southwest": {
            "lat": 36.18004912010727,
            "lng": 137.9610543701072
          }
        }
      },
      "icon": "https://maps.gstatic.com/mapfiles/place_api/icons/v1/png_71/restaurant-71.png",
      "name": "三代目江戸前あっちゃん 村井本店",
      "photos": [
        {
          "height": 640,
          "html_attributions": [
            "<a href=\"https://maps.google.com/maps/contrib/100863797777847731120\">A Google User</a>"
          ],
          "photo_reference": "Aap_uEDvgUf6Thpg5WItNnJheiJjqqBlv1vo0zBPwh_2wk3inKDV_qkTQDgS7FGrgEn7jvde1IH-TvnWpXFFwF6-YfnB0-v7sAihmFRbPG1ufq68FsJrlpUC74gFjmTOb1mSXNsWAXnaGSyeNNB44Z6eVX1JwileRsl0u7Mfm1-WwnjuofjC",
          "width": 900
        }
      ],
      "place_id": "ChIJseRV7ncPHWAR5cUr3QcpFB0",
      "plus_code": {
        "compound_code": "5XJ6+HW 松本市、長野県",
        "global_code": "8Q8V5XJ6+HW"
      },
      "types": [
        "restaurant",
        "point_of_interest",
        "food",
        "establishment"
      ]
    }
  ],
  "status": "OK"
}