{
  "candidates": [
    {
      "business_status": "OPERATIONAL",
      "formatted_address": "日本、〒390-0851 長野県松本市島内１８５８−６",
      "geometry": {
        "location": {
          "lat": 36.24765900000001,
          "lng": 137.927838
        },
        "viewport": {
          "northeast": {
            "lat": 36.24904917989272,
            "lng": 137.9292580298927
          },
          "southwest": {
            "lat": 36.24634952010727,
            "lng": 137.9265583701072
          }
        }
      },
      "icon": "https://maps.gstatic.com/mapfiles/place_api/icons/v1/png_71/generic_business-71.png",
      "name": "ダイリュー",
      "place_id": "ChIJJTX2vowNHWARK5YubQ2HYbM",
      "plus_code": {
        "compound_code": "6WXH+24 松本市、長野県",
        "global_code": "8Q8V6WXH+24"
      },
      "types": [
        "point_of_interest",
        "establishment"
      ]
    }
  ],
  "status": "OK"
}