{
  "candidates": [
    {
      "business_status": "OPERATIONAL",
      "formatted_address": "日本、〒390-1611 長野県松本市奈川黒川渡2556−２",
      "geometry": {
        "location": {
          "lat": 36.0882652,
          "lng": 137.6771614
        },
        "viewport": {
          "northeast": {
            "lat": 36.08958467989272,
            "lng": 137.6784929798927
          },
          "southwest": {
            "lat": 36.08688502010727,
            "lng": 137.6757933201073
          }
        }
      },
      "icon": "https://maps.gstatic.com/mapfiles/place_api/icons/v1/png_71/lodging-71.png",
      "name": "川仙旅館",
      "photos": [
        {
          "height": 1536,
          "html_attributions": [
            "<a href=\"https://maps.google.com/maps/contrib/117161591010384376902\">A Google User</a>"
          ],
          "photo_reference": "Aap_uEBrsWvZqn5XBWFPnoWpNPscfE8JXWzFeEiJxo_aoOGavGkNijvSvR9O6_-LxXn-9Oar17mElvBMRI-mKmfPC9pNVPb-RdgXPWMKF2N6teMgrYwX6SS17Jg933Eh-flf5NwunIdTZCKJjHWvWR-4k5_c8GTq9H40bF4i0cvFFhorDqR8",
          "width": 2048
        }
      ],
      "place_id": "ChIJpUyqdYM7HWAR5BBqZyVGbfk",
      "plus_code": {
        "compound_code": "3MQG+8W 松本市、長野県",
        "global_code": "8Q8V3MQG+8W"
      },
      "types": [
        "lodging",
        "point_of_interest",
        "establishment"
      ]
    }
  ],
  "status": "OK"
}