[
  {
    "address_components": [
      {
        "long_name": "３３０３",
        "short_name": "３３０３",
        "types": [
          "premise"
        ]
      },
      {
        "long_name": "大町",
        "short_name": "大町",
        "types": [
          "political",
          "sublocality",
          "sublocality_level_2"
        ]
      },
      {
        "long_name": "大町市",
        "short_name": "大町市",
        "types": [
          "locality",
          "political"
        ]
      },
      {
        "long_name": "長野県",
        "short_name": "長野県",
        "types": [
          "administrative_area_level_1",
          "political"
        ]
      },
      {
        "long_name": "日本",
        "short_name": "JP",
        "types": [
          "country",
          "political"
        ]
      },
      {
        "long_name": "398-0002",
        "short_name": "398-0002",
        "types": [
          "postal_code"
        ]
      }
    ],
    "formatted_address": "日本、〒398-0002 長野県大町市大町３３０３",
    "geometry": {
      "location": {
        "lat": 36.5032937,
        "lng": 137.8598633
      },
      "location_type": "ROOFTOP",
      "viewport": {
        "northeast": {
          "lat": 36.5046336302915,
          "lng": 137.8612151802915
        },
        "southwest": {
          "lat": 36.5019356697085,
          "lng": 137.8585172197085
        }
      }
    },
    "place_id": "ChIJJ0QlfepjHWAR3YSauEH4WTQ",
    "plus_code": {
      "compound_code": "GV35+8W 長野県大町市",
      "global_code": "8Q8VGV35+8W"
    },
    "types": [
      "street_address"
    ]
  }
]