{
  "candidates": [
    {
      "business_status": "OPERATIONAL",
      "formatted_address": "日本、〒399-9211 長野県北安曇郡白馬村飯田２２１８４−１０",
      "geometry": {
        "location": {
          "lat": 36.6635889,
          "lng": 137.8357556
        },
        "viewport": {
          "northeast": {
            "lat": 36.66494397989272,
            "lng": 137.8371057298927
          },
          "southwest": {
            "lat": 36.66224432010728,
            "lng": 137.8344060701073
          }
        }
      },
      "icon": "https://maps.gstatic.com/mapfiles/place_api/icons/v1/png_71/generic_business-71.png",
      "name": "白馬五竜テレキャビン",
      "photos": [
        {
          "height": 2250,
          "html_attributions": [
            "<a href=\"https://maps.google.com/maps/contrib/111370796836556424367\">Higuchi Shigehisa</a>"
          ],
          "photo_reference": "Aap_uEAY_wM-sikGg_hCeTz2zGVo72pOeZMn-P6CYEbdoyH1P7VgRXIWKCe34l3w9L3MEa2cw0L2Wi46K0vc5cMwnx3rqseVLR-JdxEC_lP7a06Qms5b_d0mIQMujHiH47GzsELKKylalbTUkmtGehC1Teq4eJqnlmAwfxyB5FU0wzO-bxmt",
          "width": 4000
        }
      ],
      "place_id": "ChIJo40vBFLQ918RfccRBuPvZEM",
      "plus_code": {
        "compound_code": "MR7P+C8 白馬村、長野県",
        "global_code": "8Q8VMR7P+C8"
      },
      "types": [
        "tourist_attraction",
        "point_of_interest",
        "establishment"
      ]
    }
  ],
  "status": "OK"
}