{
  "candidates": [
    {
      "formatted_address": "日本、〒399-9301 長野県北安曇郡白馬村北城７０７１−２",
      "geometry": {
        "location": {
          "lat": 36.6971612,
          "lng": 137.8636937
        },
        "viewport": {
          "northeast": {
            "lat": 36.69853552989272,
            "lng": 137.8649691798927
          },
          "southwest": {
            "lat": 36.69583587010728,
            "lng": 137.8622695201073
          }
        }
      },
      "icon": "https://maps.gstatic.com/mapfiles/place_api/icons/v1/png_71/geocode-71.png",
      "name": "〒399-9301 長野県北安曇郡白馬村北城７０７１−２",
      "place_id": "ChIJm06jJwTS918ReiZE-QMdP6c",
      "plus_code": {
        "compound_code": "MVW7+VF 白馬村、長野県",
        "global_code": "8Q8VMVW7+VF"
      },
      "types": [
        "street_address"
      ]
    }
  ],
  "status": "OK"
}