{
  "candidates": [
    {
      "formatted_address": "日本、〒396-0301 長野県伊那市高遠町藤沢２２７９−１",
      "geometry": {
        "location": {
          "lat": 35.8999914,
          "lng": 138.1004379
        },
        "viewport": {
          "northeast": {
            "lat": 35.90134852989272,
            "lng": 138.1017856798927
          },
          "southwest": {
            "lat": 35.89864887010728,
            "lng": 138.0990860201073
          }
        }
      },
      "icon": "https://maps.gstatic.com/mapfiles/place_api/icons/v1/png_71/geocode-71.png",
      "name": "〒396-0301 長野県伊那市高遠町藤沢２２７９−１",
      "place_id": "ChIJO5fA0_JYHGARFVmIQS8Q1vc",
      "plus_code": {
        "compound_code": "V4X2+X5 伊那市、長野県",
        "global_code": "8Q7WV4X2+X5"
      },
      "types": [
        "street_address"
      ]
    }
  ],
  "status": "OK"
}