{
  "candidates": [
    {
      "formatted_address": "日本、〒394-0081 長野県岡谷市長地権現町２丁目１−５８",
      "geometry": {
        "location": {
          "lat": 36.06636719999999,
          "lng": 138.0714773
        },
        "viewport": {
          "northeast": {
            "lat": 36.06762327989272,
            "lng": 138.0728153298927
          },
          "southwest": {
            "lat": 36.06492362010728,
            "lng": 138.0701156701073
          }
        }
      },
      "icon": "https://maps.gstatic.com/mapfiles/place_api/icons/v1/png_71/geocode-71.png",
      "name": "〒394-0081 長野県岡谷市長地権現町２丁目１−５８",
      "place_id": "ChIJ0bykvPr_HGAReLlAGy6gIwI",
      "types": [
        "premise"
      ]
    }
  ],
  "status": "OK"
}