[
  {
    "address_components": [
      {
        "long_name": "９８１１",
        "short_name": "９８１１",
        "types": [
          "premise"
        ]
      },
      {
        "long_name": "横落",
        "short_name": "横落",
        "types": [
          "political",
          "sublocality",
          "sublocality_level_2"
        ]
      },
      {
        "long_name": "野沢温泉村",
        "short_name": "野沢温泉村",
        "types": [
          "locality",
          "political"
        ]
      },
      {
        "long_name": "下高井郡",
        "short_name": "下高井郡",
        "types": [
          "administrative_area_level_2",
          "political"
        ]
      },
      {
        "long_name": "長野県",
        "short_name": "長野県",
        "types": [
          "administrative_area_level_1",
          "political"
        ]
      },
      {
        "long_name": "日本",
        "short_name": "JP",
        "types": [
          "country",
          "political"
        ]
      },
      {
        "long_name": "389-2502",
        "short_name": "389-2502",
        "types": [
          "postal_code"
        ]
      }
    ],
    "formatted_address": "日本、〒389-2502 長野県下高井郡野沢温泉村横落９８１１",
    "geometry": {
      "location": {
        "lat": 36.9226015,
        "lng": 138.4433432
      },
      "location_type": "ROOFTOP",
      "viewport": {
        "northeast": {
          "lat": 36.9238856802915,
          "lng": 138.4447579302915
        },
        "southwest": {
          "lat": 36.9211877197085,
          "lng": 138.4420599697085
        }
      }
    },
    "partial_match": true,
    "place_id": "ChIJz_X0dRMF9l8RXAY7PZlJFg8",
    "plus_code": {
      "compound_code": "WCFV+28 長野県野沢温泉村",
      "global_code": "8Q8WWCFV+28"
    },
    "types": [
      "establishment",
      "parking",
      "point_of_interest"
    ]
  }
]