{
  "candidates": [
    {
      "business_status": "OPERATIONAL",
      "formatted_address": "日本、〒395-1108 長野県下伊那郡喬木村伊久間１５１７９",
      "geometry": {
        "location": {
          "lat": 35.5154228,
          "lng": 137.8685349
        },
        "viewport": {
          "northeast": {
            "lat": 35.51678347989272,
            "lng": 137.8699156298927
          },
          "southwest": {
            "lat": 35.51408382010727,
            "lng": 137.8672159701073
          }
        }
      },
      "icon": "https://maps.gstatic.com/mapfiles/place_api/icons/v1/png_71/shopping-71.png",
      "name": "第一チキン",
      "photos": [
        {
          "height": 960,
          "html_attributions": [
            "<a href=\"https://maps.google.com/maps/contrib/117672052166129741569\">平沢久義</a>"
          ],
          "photo_reference": "Aap_uEB_SsxQtYrIwWNKmepNbZ-CQT56hT0F1IO7lM7KnDG7pZ_It4JvDwggDCMD0JANkatXzW3eDpCKuIhfL9mPV_0d119AjzGpSDQve9MwxxXa-dsMulcSdGl1pRP8FmmqBUHYxhKO9Q9XZyGnpM6Iq_EvGsl_R-n_qBELJ7qWmBXsQ8Fe",
          "width": 1706
        }
      ],
      "place_id": "ChIJZaEo5rObHGARw5AQDle_eRU",
      "plus_code": {
        "compound_code": "GV89+5C 喬木村、長野県",
        "global_code": "8Q7VGV89+5C"
      },
      "types": [
        "food",
        "store",
        "point_of_interest",
        "establishment"
      ]
    }
  ],
  "status": "OK"
}