{
  "candidates": [
    {
      "formatted_address": "日本、〒399-3202 長野県下伊那郡豊丘村神稲１２４１０",
      "geometry": {
        "location": {
          "lat": 35.544439,
          "lng": 137.8908847
        },
        "viewport": {
          "northeast": {
            "lat": 35.54582677989272,
            "lng": 137.8921135798927
          },
          "southwest": {
            "lat": 35.54312712010727,
            "lng": 137.8894139201073
          }
        }
      },
      "icon": "https://maps.gstatic.com/mapfiles/place_api/icons/v1/png_71/geocode-71.png",
      "name": "〒399-3202 長野県下伊那郡豊丘村神稲１２４１０",
      "place_id": "ChIJwygEXvKaHGARAzJUenOkSO4",
      "plus_code": {
        "compound_code": "GVVR+Q9 豊丘村、長野県",
        "global_code": "8Q7VGVVR+Q9"
      },
      "types": [
        "street_address"
      ]
    }
  ],
  "status": "OK"
}