{
  "candidates": [
    {
      "business_status": "OPERATIONAL",
      "formatted_address": "日本、〒393-0000 長野県諏訪郡下諏訪町 八島湿原10618",
      "geometry": {
        "location": {
          "lat": 36.1198825,
          "lng": 138.1591708
        },
        "viewport": {
          "northeast": {
            "lat": 36.12131567989272,
            "lng": 138.1605231298927
          },
          "southwest": {
            "lat": 36.11861602010728,
            "lng": 138.1578234701072
          }
        }
      },
      "icon": "https://maps.gstatic.com/mapfiles/place_api/icons/v1/png_71/lodging-71.png",
      "name": "八島山荘",
      "photos": [
        {
          "height": 3264,
          "html_attributions": [
            "<a href=\"https://maps.google.com/maps/contrib/102273147274223246384\">A Google User</a>"
          ],
          "photo_reference": "Aap_uEANFZoLuN3juplj3ySb76MkA3kb0wh2_N-eY5I1Bck6gsQSNCzRAZqDCIrqnhn0JYcbzBF_-dgOatKmfaRz0NIHWVe-T0LuIIwoo_-a5BYiiY_TMyc4H_Exmy1SAGMktHqEuh1mJeFOMKlgQbcMRmUNWK961pdRXo39h6XZmiRd-wLn",
          "width": 4928
        }
      ],
      "place_id": "ChIJYUKnw1erHWARloV8f9Z37ik",
      "plus_code": {
        "compound_code": "4595+XM 下諏訪町、長野県",
        "global_code": "8Q8W4595+XM"
      },
      "types": [
        "lodging",
        "point_of_interest",
        "establishment"
      ]
    }
  ],
  "status": "OK"
}