{
  "candidates": [
    {
      "business_status": "OPERATIONAL",
      "formatted_address": "日本、〒391-0001 長野県茅野市ちの７０２１",
      "geometry": {
        "location": {
          "lat": 35.992492,
          "lng": 138.153084
        },
        "viewport": {
          "northeast": {
            "lat": 35.99384972989272,
            "lng": 138.1544598798928
          },
          "southwest": {
            "lat": 35.99115007010727,
            "lng": 138.1517602201073
          }
        }
      },
      "icon": "https://maps.gstatic.com/mapfiles/place_api/icons/v1/png_71/restaurant-71.png",
      "name": "茅野駅前 本手打ちそば 更科",
      "photos": [
        {
          "height": 2160,
          "html_attributions": [
            "<a href=\"https://maps.google.com/maps/contrib/104341003640143945500\">x10a zgmf</a>"
          ],
          "photo_reference": "Aap_uEDqoCcuv0ig0pCAr_z_KPiNfRaUVT-3J6xlm4395Sw7xdSnLkzQKVhKGG29XgDqt064HJqN36lW606huVFS_Ykz-x7VUVs0-C46h2HJGcdnbpe8w8Oe0p9q9mVB2JYs1fHQXFskb21vbNr9Uw7e-HDafOMmX877eCIWNC3cEn2xbtXn",
          "width": 3840
        }
      ],
      "place_id": "ChIJvUA02DFXHGARHoqDAy_PeD8",
      "plus_code": {
        "compound_code": "X5R3+X6 茅野市、長野県",
        "global_code": "8Q7WX5R3+X6"
      },
      "types": [
        "restaurant",
        "food",
        "point_of_interest",
        "establishment"
      ]
    },
    {
      "business_status": "OPERATIONAL",
      "formatted_address": "日本、〒391-0216 長野県茅野市米沢７６９８",
      "geometry": {
        "location": {
          "lat": 36.0327978,
          "lng": 138.1967016
        },
        "viewport": {
          "northeast": {
            "lat": 36.03414012989272,
            "lng": 138.1980610298927
          },
          "southwest": {
            "lat": 36.03144047010728,
            "lng": 138.1953613701073
          }
        }
      },
      "icon": "https://maps.gstatic.com/mapfiles/place_api/icons/v1/png_71/restaurant-71.png",
      "name": "長寿更科",
      "photos": [
        {
          "height": 2160,
          "html_attributions": [
            "<a href=\"https://maps.google.com/maps/contrib/105376039263506131130\">Satoru Shibano</a>"
          ],
          "photo_reference": "Aap_uEBi74j5Oig0lRHGdhp5_GROm_933ToiI28rGVTj70j0BAHaE3MYZxYcd-BIyTE6tnNjOhh3EPyS9nJCq4KsoO-bH86r6nOG6Xnw4Qj_aOGRk_rMO8VoDBP4bvdsT6m9lPg8KtkE2lJ81bRWtnVGLekuSLXvRlFZwL35A5Uky4y_tK_F",
          "width": 3840
        }
      ],
      "place_id": "ChIJHY5ecQlRHGAR6TXr-Tgrm50",
      "plus_code": {
        "compound_code": "25MW+5M 茅野市、長野県",
        "global_code": "8Q8W25MW+5M"
      },
      "types": [
        "restaurant",
        "food",
        "point_of_interest",
        "establishment"
      ]
    }
  ],
  "status": "OK"
}