[
  {
    "address_components": [
      {
        "long_name": "３",
        "short_name": "３",
        "types": [
          "premise"
        ]
      },
      {
        "long_name": "３",
        "short_name": "３",
        "types": [
          "political",
          "sublocality",
          "sublocality_level_4"
        ]
      },
      {
        "long_name": "中央",
        "short_name": "中央",
        "types": [
          "political",
          "sublocality",
          "sublocality_level_2"
        ]
      },
      {
        "long_name": "駒ヶ根市",
        "short_name": "駒ヶ根市",
        "types": [
          "locality",
          "political"
        ]
      },
      {
        "long_name": "長野県",
        "short_name": "長野県",
        "types": [
          "administrative_area_level_1",
          "political"
        ]
      },
      {
        "long_name": "日本",
        "short_name": "JP",
        "types": [
          "country",
          "political"
        ]
      },
      {
        "long_name": "399-4112",
        "short_name": "399-4112",
        "types": [
          "postal_code"
        ]
      }
    ],
    "formatted_address": "日本、〒399-4112 長野県駒ヶ根市中央３−３",
    "geometry": {
      "location": {
        "lat": 35.73626040000001,
        "lng": 137.9358392
      },
      "location_type": "ROOFTOP",
      "viewport": {
        "northeast": {
          "lat": 35.7376110302915,
          "lng": 137.9371516302915
        },
        "southwest": {
          "lat": 35.7349130697085,
          "lng": 137.9344536697085
        }
      }
    },
    "partial_match": true,
    "place_id": "ChIJX0-exrDyHGARIuRUafNWAWc",
    "plus_code": {
      "compound_code": "PWPP+G8 長野県駒ヶ根市",
      "global_code": "8Q7VPWPP+G8"
    },
    "types": [
      "establishment",
      "food",
      "point_of_interest",
      "store"
    ]
  }
]