{
  "candidates": [
    {
      "business_status": "OPERATIONAL",
      "formatted_address": "日本、〒381-0032 長野県長野市若宮２丁目１３−５",
      "geometry": {
        "location": {
          "lat": 36.6472713,
          "lng": 138.2283076
        },
        "viewport": {
          "northeast": {
            "lat": 36.64856377989273,
            "lng": 138.2297518298927
          },
          "southwest": {
            "lat": 36.64586412010728,
            "lng": 138.2270521701073
          }
        }
      },
      "icon": "https://maps.gstatic.com/mapfiles/place_api/icons/v1/png_71/restaurant-71.png",
      "name": "スシロー 長野若宮店",
      "photos": [
        {
          "height": 2160,
          "html_attributions": [
            "<a href=\"https://maps.google.com/maps/contrib/100909006395912590393\">KAZUNORI KAWAKUBO</a>"
          ],
          "photo_reference": "Aap_uEBg_jEPzkzDBksvaDWMxM0x4Sia57gShVRq-kzsORw1BBPBFdCffpuEMNyODBdR2WYxS738B_8ZG5UEnwdrd-_AWTPyvsuog0ZIR-hPh-UuMrvHkw1bSQb9MIY1YxpEYY_WBRvTQjEsuEBR4tjHeV1zXILHGH9Rmg5zbMjohFOKHsfv",
          "width": 3840
        }
      ],
      "place_id": "ChIJCXJgkwiGHWARnx9Hmhy3hOY",
      "plus_code": {
        "compound_code": "J6WH+W8 長野市、長野県",
        "global_code": "8Q8WJ6WH+W8"
      },
      "types": [
        "restaurant",
        "point_of_interest",
        "food",
        "establishment"
      ]
    }
  ],
  "status": "OK"
}