{
  "candidates": [
    {
      "formatted_address": "日本、〒380-0836 長野県長野市大字南長野南県町南県町１１３０−８ ＫＩＴＣＨＥＮ３６５",
      "geometry": {
        "location": {
          "lat": 36.64951,
          "lng": 138.1850421
        },
        "viewport": {
          "northeast": {
            "lat": 36.65093642989272,
            "lng": 138.1864114798927
          },
          "southwest": {
            "lat": 36.64823677010727,
            "lng": 138.1837118201073
          }
        }
      },
      "icon": "https://maps.gstatic.com/mapfiles/place_api/icons/v1/png_71/geocode-71.png",
      "name": "ＫＩＴＣＨＥＮ３６５",
      "place_id": "ChIJT_vGzu6GHWAROqSbG9V1kiw",
      "types": [
        "premise"
      ]
    }
  ],
  "status": "OK"
}