{
  "candidates": [
    {
      "business_status": "OPERATIONAL",
      "formatted_address": "日本、〒380-0823 長野県長野市南千歳１丁目２２−１４",
      "geometry": {
        "location": {
          "lat": 36.6441853,
          "lng": 138.1884365
        },
        "viewport": {
          "northeast": {
            "lat": 36.64556972989272,
            "lng": 138.1897508298927
          },
          "southwest": {
            "lat": 36.64287007010728,
            "lng": 138.1870511701073
          }
        }
      },
      "icon": "https://maps.gstatic.com/mapfiles/place_api/icons/v1/png_71/restaurant-71.png",
      "name": "りんごの木 長野駅前店",
      "photos": [
        {
          "height": 9548,
          "html_attributions": [
            "<a href=\"https://maps.google.com/maps/contrib/113509286124421779007\">furukawa hiroyuki</a>"
          ],
          "photo_reference": "Aap_uEDp2rOcPvda3YPnvqD47w83SBtxIkAr1TWwlpg2G6qiriFsA-vSRR6QOIDb9kDeZ7T6rO6icNYOfysa4lyzaoYHMC1hBPvlBTaPCBfa-2Qf-qLK3dSOIa1gR93-0PJh8D8j--UYyJw6PcZN5t61PExK7SAfKSG66F7d9wRMQAiAOJ8r",
          "width": 6483
        }
      ],
      "place_id": "ChIJnc8wv5KGHWARVZSYgQZUeqE",
      "plus_code": {
        "compound_code": "J5VQ+M9 長野市、長野県",
        "global_code": "8Q8WJ5VQ+M9"
      },
      "types": [
        "bakery",
        "store",
        "food",
        "point_of_interest",
        "establishment"
      ]
    }
  ],
  "status": "OK"
}