[
  {
    "address_components": [
      {
        "long_name": "2f",
        "short_name": "2f",
        "types": [
          "subpremise"
        ]
      },
      {
        "long_name": "３−７",
        "short_name": "３−７",
        "types": [
          "premise"
        ]
      },
      {
        "long_name": "１丁目",
        "short_name": "１丁目",
        "types": [
          "political",
          "sublocality",
          "sublocality_level_3"
        ]
      },
      {
        "long_name": "南千歳",
        "short_name": "南千歳",
        "types": [
          "political",
          "sublocality",
          "sublocality_level_2"
        ]
      },
      {
        "long_name": "長野市",
        "short_name": "長野市",
        "types": [
          "locality",
          "political"
        ]
      },
      {
        "long_name": "長野県",
        "short_name": "長野県",
        "types": [
          "administrative_area_level_1",
          "political"
        ]
      },
      {
        "long_name": "日本",
        "short_name": "JP",
        "types": [
          "country",
          "political"
        ]
      },
      {
        "long_name": "380-0823",
        "short_name": "380-0823",
        "types": [
          "postal_code"
        ]
      }
    ],
    "formatted_address": "日本、〒380-0823 長野県長野市南千歳１丁目３−７ 2f",
    "geometry": {
      "bounds": {
        "northeast": {
          "lat": 36.6461431,
          "lng": 138.1889308
        },
        "southwest": {
          "lat": 36.6458865,
          "lng": 138.1886886
        }
      },
      "location": {
        "lat": 36.6460111,
        "lng": 138.1887996
      },
      "location_type": "ROOFTOP",
      "viewport": {
        "northeast": {
          "lat": 36.64736378029149,
          "lng": 138.1901629802915
        },
        "southwest": {
          "lat": 36.64466581970849,
          "lng": 138.1874650197085
        }
      }
    },
    "partial_match": true,
    "place_id": "EjcyZiwgMS1jaMWNbWUtMy03IE1pbmFtaWNoaXRvc2UsIE5hZ2FubywgMzgwLTA4MjMsIEphcGFuIh4aHAoWChQKEglJ_3tE7YYdYBES0u-96iwSNBICMmY",
    "types": [
      "subpremise"
    ]
  },
  {
    "address_components": [
      {
        "long_name": "１７",
        "short_name": "１７",
        "types": [
          "political",
          "sublocality",
          "sublocality_level_4"
        ]
      },
      {
        "long_name": "１丁目",
        "short_name": "１丁目",
        "types": [
          "political",
          "sublocality",
          "sublocality_level_3"
        ]
      },
      {
        "long_name": "松前台",
        "short_name": "松前台",
        "types": [
          "political",
          "sublocality",
          "sublocality_level_2"
        ]
      },
      {
        "long_name": "守谷市",
        "short_name": "守谷市",
        "types": [
          "locality",
          "political"
        ]
      },
      {
        "long_name": "茨城県",
        "short_name": "茨城県",
        "types": [
          "administrative_area_level_1",
          "political"
        ]
      },
      {
        "long_name": "日本",
        "short_name": "JP",
        "types": [
          "country",
          "political"
        ]
      },
      {
        "long_name": "302-0102",
        "short_name": "302-0102",
        "types": [
          "postal_code"
        ]
      }
    ],
    "formatted_address": "日本、〒302-0102 茨城県守谷市松前台１丁目１７",
    "geometry": {
      "location": {
        "lat": 35.9672612,
        "lng": 139.9668817
      },
      "location_type": "ROOFTOP",
      "viewport": {
        "northeast": {
          "lat": 35.9685317302915,
          "lng": 139.9682556302915
        },
        "southwest": {
          "lat": 35.9658337697085,
          "lng": 139.9655576697085
        }
      }
    },
    "partial_match": true,
    "place_id": "ChIJ3zQruxKfGGAR8yhdIr9Arb0",
    "plus_code": {
      "compound_code": "XX88+WQ 茨城県守谷市",
      "global_code": "8Q7XXX88+WQ"
    },
    "types": [
      "establishment",
      "health",
      "hospital",
      "point_of_interest"
    ]
  }
]