[
  {
    "address_components": [
      {
        "long_name": "５",
        "short_name": "５",
        "types": [
          "premise"
        ]
      },
      {
        "long_name": "１３５５",
        "short_name": "１３５５",
        "types": [
          "political",
          "sublocality",
          "sublocality_level_4"
        ]
      },
      {
        "long_name": "末広町",
        "short_name": "末広町",
        "types": [
          "political",
          "sublocality",
          "sublocality_level_3"
        ]
      },
      {
        "long_name": "南長野",
        "short_name": "南長野",
        "types": [
          "political",
          "sublocality",
          "sublocality_level_2"
        ]
      },
      {
        "long_name": "長野市",
        "short_name": "長野市",
        "types": [
          "locality",
          "political"
        ]
      },
      {
        "long_name": "長野県",
        "short_name": "長野県",
        "types": [
          "administrative_area_level_1",
          "political"
        ]
      },
      {
        "long_name": "日本",
        "short_name": "JP",
        "types": [
          "country",
          "political"
        ]
      },
      {
        "long_name": "380-0825",
        "short_name": "380-0825",
        "types": [
          "postal_code"
        ]
      }
    ],
    "formatted_address": "日本、〒380-0825 長野県長野市南長野末広町１３５５−５",
    "geometry": {
      "location": {
        "lat": 36.6435341,
        "lng": 138.1869837
      },
      "location_type": "ROOFTOP",
      "viewport": {
        "northeast": {
          "lat": 36.6448588302915,
          "lng": 138.1883686302915
        },
        "southwest": {
          "lat": 36.6421608697085,
          "lng": 138.1856706697085
        }
      }
    },
    "partial_match": true,
    "place_id": "ChIJ5SEdJ5OGHWARyjHm6TuPnSk",
    "plus_code": {
      "compound_code": "J5VP+CQ 日本、長野県長野市",
      "global_code": "8Q8WJ5VP+CQ"
    },
    "types": [
      "establishment",
      "point_of_interest"
    ]
  }
]